{
	"completely_empty": false,
	"image": {
		"height": 720,
		"scale": 1.66796875,
		"width": 1280
	},
	"mark": [
		{
			"class_idx": 3,
			"name": "L-Intersection",
			"points": [
				{
					"int_x": 482,
					"int_y": 1,
					"x": 0.3764902241297091,
					"y": 0.0016949152542372883
				},
				{
					"int_x": 498,
					"int_y": 1,
					"x": 0.38936576061039585,
					"y": 0.0016949152542372883
				},
				{
					"int_x": 498,
					"int_y": 7,
					"x": 0.38936576061039585,
					"y": 0.010169491525423728
				},
				{
					"int_x": 482,
					"int_y": 7,
					"x": 0.3764902241297091,
					"y": 0.010169491525423728
				}
			],
			"rect": {
				"h": 0.008474576271186439,
				"int_h": 7,
				"int_w": 17,
				"int_x": 482,
				"int_y": 1,
				"w": 0.012875536480686733,
				"x": 0.3764902241297091,
				"y": 0.0016949152542372883
			}
		},
		{
			"class_idx": 4,
			"name": "T-Intersection",
			"points": [
				{
					"int_x": 250,
					"int_y": 34,
					"x": 0.19504053409632807,
					"y": 0.046610169491525424
				},
				{
					"int_x": 272,
					"int_y": 34,
					"x": 0.212207916070577,
					"y": 0.046610169491525424
				},
				{
					"int_x": 272,
					"int_y": 47,
					"x": 0.212207916070577,
					"y": 0.06525423728813559
				},
				{
					"int_x": 250,
					"int_y": 47,
					"x": 0.19504053409632807,
					"y": 0.06525423728813559
				}
			],
			"rect": {
				"h": 0.018644067796610167,
				"int_h": 14,
				"int_w": 23,
				"int_x": 250,
				"int_y": 34,
				"w": 0.01716738197424894,
				"x": 0.19504053409632807,
				"y": 0.046610169491525424
			}
		},
		{
			"class_idx": 5,
			"name": "X-Intersection",
			"points": [
				{
					"int_x": 709,
					"int_y": 39,
					"x": 0.5541249403910349,
					"y": 0.05423728813559322
				},
				{
					"int_x": 730,
					"int_y": 39,
					"x": 0.5703385789222699,
					"y": 0.05423728813559322
				},
				{
					"int_x": 730,
					"int_y": 51,
					"x": 0.5703385789222699,
					"y": 0.0711864406779661
				},
				{
					"int_x": 709,
					"int_y": 51,
					"x": 0.5541249403910349,
					"y": 0.0711864406779661
				}
			],
			"rect": {
				"h": 0.016949152542372885,
				"int_h": 13,
				"int_w": 22,
				"int_x": 709,
				"int_y": 39,
				"w": 0.01621363853123503,
				"x": 0.5541249403910349,
				"y": 0.05423728813559322
			}
		},
		{
			"class_idx": 2,
			"name": "robot",
			"points": [
				{
					"int_x": 885,
					"int_y": 0,
					"x": 0.6917024320457796,
					"y": 0.0
				},
				{
					"int_x": 1028,
					"int_y": 0,
					"x": 0.8028135431568908,
					"y": 0.0
				},
				{
					"int_x": 1028,
					"int_y": 142,
					"x": 0.8028135431568908,
					"y": 0.19661016949152543
				},
				{
					"int_x": 885,
					"int_y": 142,
					"x": 0.6917024320457796,
					"y": 0.19661016949152543
				}
			],
			"rect": {
				"h": 0.19661016949152543,
				"int_h": 143,
				"int_w": 144,
				"int_x": 885,
				"int_y": 0,
				"w": 0.11111111111111116,
				"x": 0.6917024320457796,
				"y": 0.0
			}
		},
		{
			"class_idx": 5,
			"name": "X-Intersection",
			"points": [
				{
					"int_x": 1037,
					"int_y": 43,
					"x": 0.8104434907010014,
					"y": 0.059322033898305086
				},
				{
					"int_x": 1064,
					"int_y": 43,
					"x": 0.8309489747257988,
					"y": 0.059322033898305086
				},
				{
					"int_x": 1064,
					"int_y": 56,
					"x": 0.8309489747257988,
					"y": 0.07796610169491526
				},
				{
					"int_x": 1037,
					"int_y": 56,
					"x": 0.8104434907010014,
					"y": 0.07796610169491526
				}
			],
			"rect": {
				"h": 0.018644067796610174,
				"int_h": 14,
				"int_w": 28,
				"int_x": 1037,
				"int_y": 43,
				"w": 0.02050548402479735,
				"x": 0.8104434907010014,
				"y": 0.059322033898305086
			}
		},
		{
			"class_idx": 5,
			"name": "X-Intersection",
			"points": [
				{
					"int_x": 1042,
					"int_y": 218,
					"x": 0.8142584644730568,
					"y": 0.30338983050847457
				},
				{
					"int_x": 1145,
					"int_y": 218,
					"x": 0.8948497854077253,
					"y": 0.30338983050847457
				},
				{
					"int_x": 1145,
					"int_y": 250,
					"x": 0.8948497854077253,
					"y": 0.34745762711864403
				},
				{
					"int_x": 1042,
					"int_y": 250,
					"x": 0.8142584644730568,
					"y": 0.34745762711864403
				}
			],
			"rect": {
				"h": 0.04406779661016946,
				"int_h": 33,
				"int_w": 104,
				"int_x": 1042,
				"int_y": 218,
				"w": 0.08059132093466848,
				"x": 0.8142584644730568,
				"y": 0.30338983050847457
			}
		},
		{
			"class_idx": 0,
			"name": "ball",
			"points": [
				{
					"int_x": 579,
					"int_y": 223,
					"x": 0.452551263710062,
					"y": 0.3097457627118644
				},
				{
					"int_x": 701,
					"int_y": 223,
					"x": 0.547925608011445,
					"y": 0.3097457627118644
				},
				{
					"int_x": 701,
					"int_y": 341,
					"x": 0.547925608011445,
					"y": 0.4733050847457627
				},
				{
					"int_x": 579,
					"int_y": 341,
					"x": 0.452551263710062,
					"y": 0.4733050847457627
				}
			],
			"rect": {
				"h": 0.16355932203389834,
				"int_h": 119,
				"int_w": 123,
				"int_x": 579,
				"int_y": 223,
				"w": 0.09537434430138297,
				"x": 0.452551263710062,
				"y": 0.3097457627118644
			}
		},
		{
			"class_idx": 3,
			"name": "L-Intersection",
			"points": [
				{
					"int_x": 27,
					"int_y": 324,
					"x": 0.02098235574630425,
					"y": 0.45042372881355935
				},
				{
					"int_x": 79,
					"int_y": 324,
					"x": 0.061993323795898905,
					"y": 0.45042372881355935
				},
				{
					"int_x": 79,
					"int_y": 363,
					"x": 0.061993323795898905,
					"y": 0.503813559322034
				},
				{
					"int_x": 27,
					"int_y": 363,
					"x": 0.02098235574630425,
					"y": 0.503813559322034
				}
			],
			"rect": {
				"h": 0.05338983050847462,
				"int_h": 40,
				"int_w": 53,
				"int_x": 27,
				"int_y": 324,
				"w": 0.04101096804959466,
				"x": 0.02098235574630425,
				"y": 0.45042372881355935
			}
		},
		{
			"class_idx": 0,
			"name": "ball",
			"points": [
				{
					"int_x": 852,
					"int_y": 0,
					"x": 0.6655737704918032,
					"y": 0.0
				},
				{
					"int_x": 870,
					"int_y": 0,
					"x": 0.6796252927400468,
					"y": 0.0
				},
				{
					"int_x": 870,
					"int_y": 15,
					"x": 0.6796252927400468,
					"y": 0.020815986677768523
				},
				{
					"int_x": 852,
					"int_y": 15,
					"x": 0.6655737704918032,
					"y": 0.020815986677768523
				}
			],
			"rect": {
				"h": 0.020815986677768523,
				"int_h": 16,
				"int_w": 19,
				"int_x": 852,
				"int_y": 0,
				"w": 0.014051522248243575,
				"x": 0.6655737704918032,
				"y": 0.0
			}
		}
	],
	"timestamp": 1761254886,
	"version": "1.10.18-1"
}
